
{"order":100,"items":[{"name":"Audio","href":"audio.html","topicHref":"audio.html"},{"name":"Bone","href":"bone.html","topicHref":"bone.html"},{"name":"Button","href":"button.html","topicHref":"button.html"},{"name":"Frame","href":"frame.html","topicHref":"frame.html"},{"name":"ImageCombiner","href":"image_combiner.html","topicHref":"image_combiner.html"},{"name":"Movie","href":"movie.html","topicHref":"movie.html"},{"name":"Slider","href":"slider.html","topicHref":"slider.html"},{"name":"Widget","href":"widget.html","topicHref":"widget.html"},{"name":"3D","includedFrom":"~/articles/tangerine/node/3d/toc.yml","items":[{"name":"Camera3D","href":"3d/camera_3d.html","topicHref":"3d/camera_3d.html"},{"name":"Model3D","href":"3d/model_3d.html","topicHref":"3d/model_3d.html"},{"name":"Node3D","href":"3d/node_3d.html","topicHref":"3d/node_3d.html"},{"name":"Viewport3D","href":"3d/viewport_3d.html","topicHref":"3d/viewport_3d.html"},{"name":"WidgetAdapter3D","href":"3d/widget_adapter_3d.html","topicHref":"3d/widget_adapter_3d.html"},{"name":"Spline3D","includedFrom":"~/articles/tangerine/node/3d/spline_3d/toc.yml","items":[{"name":"Spline3D","href":"3d/spline_3d/spline_3d.html","topicHref":"3d/spline_3d/spline_3d.html"},{"name":"SplineGear3D","href":"3d/spline_3d/spline_gear_3d.html","topicHref":"3d/spline_3d/spline_gear_3d.html"},{"name":"SplinePoint3D","href":"3d/spline_3d/spline_point_3d.html","topicHref":"3d/spline_3d/spline_point_3d.html"}]}]},{"name":"Image","includedFrom":"~/articles/tangerine/node/image/toc.yml","items":[{"name":"DistortionMesh","href":"image/distortion_mesh.html","topicHref":"image/distortion_mesh.html"},{"name":"Image","href":"image/image.html","topicHref":"image/image.html"},{"name":"NineGrid","href":"image/nine_grid.html","topicHref":"image/nine_grid.html"},{"name":"TiledImage","href":"image/tiled_image.html","topicHref":"image/tiled_image.html"}]},{"name":"Particles","includedFrom":"~/articles/tangerine/node/particles/toc.yml","items":[{"name":"EmitterShapePoint","href":"particles/emitter_shape_point.html","topicHref":"particles/emitter_shape_point.html"},{"name":"ParticleEmitter","href":"particles/particle_emitter.html","topicHref":"particles/particle_emitter.html"},{"name":"ParticleModifier","href":"particles/particle_modifier.html","topicHref":"particles/particle_modifier.html"},{"name":"ParticlesMagnet","href":"particles/particles_magnet.html","topicHref":"particles/particles_magnet.html"}]},{"name":"Polyline","includedFrom":"~/articles/tangerine/node/polyline/toc.yml","items":[{"name":"Polyline","href":"polyline/polyline.html","topicHref":"polyline/polyline.html"},{"name":"PolylinePoint","href":"polyline/polyline_point.html","topicHref":"polyline/polyline_point.html"}]},{"name":"Spline","includedFrom":"~/articles/tangerine/node/spline/toc.yml","items":[{"name":"Spline","href":"spline/spline.html","topicHref":"spline/spline.html"},{"name":"SplineGear","href":"spline/spline_gear.html","topicHref":"spline/spline_gear.html"},{"name":"SplinePoint","href":"spline/spline_point.html","topicHref":"spline/spline_point.html"}]},{"name":"Text","includedFrom":"~/articles/tangerine/node/text/toc.yml","items":[{"name":"RichText","href":"text/rich_text.html","topicHref":"text/rich_text.html"},{"name":"SimpleText","href":"text/simple_text.html","topicHref":"text/simple_text.html"},{"name":"TextStyle","href":"text/text_style.html","topicHref":"text/text_style.html"}]}]}
